sudocdkconstructs/s3_run_fargate_task/__init__.py
sudocdkconstructs/s3_run_fargate_task/py.typed
sudocdkconstructs/s3_run_fargate_task/_jsii/__init__.py
sudocdkconstructs/s3_run_fargate_task/_jsii/s3-run-fargate-task@1.0.1.jsii.tgz
sudocdkconstructs.s3_run_fargate_task-1.0.1.dist-info/LICENSE
sudocdkconstructs.s3_run_fargate_task-1.0.1.dist-info/METADATA
sudocdkconstructs.s3_run_fargate_task-1.0.1.dist-info/WHEEL
sudocdkconstructs.s3_run_fargate_task-1.0.1.dist-info/top_level.txt
sudocdkconstructs.s3_run_fargate_task-1.0.1.dist-info/RECORD
