Metadata-Version: 2.1
Name: sudocdkconstructs.s3-run-fargate-task
Version: 1.0.1
Summary: Run Fargate task with S3 upload event
Home-page: https://github.com/sudopla/cdk-constructs.git
Author: Jorge Pla
License: MIT
Project-URL: Source, https://github.com/sudopla/cdk-constructs.git
Platform: UNKNOWN
Classifier: Intended Audience :: Developers
Classifier: Operating System :: OS Independent
Classifier: Programming Language :: JavaScript
Classifier: Programming Language :: Python :: 3 :: Only
Classifier: Programming Language :: Python :: 3.6
Classifier: Programming Language :: Python :: 3.7
Classifier: Programming Language :: Python :: 3.8
Classifier: Programming Language :: Python :: 3.9
Classifier: Typing :: Typed
Classifier: License :: OSI Approved
Requires-Python: >=3.6
License-File: LICENSE
Requires-Dist: aws-cdk-lib (<3.0.0,>=2.0.0)
Requires-Dist: constructs (<11.0.0,>=10.0.0)
Requires-Dist: jsii (<2.0.0,>=1.54.0)
Requires-Dist: publication (>=0.0.3)
